ilint/__init__.py
ilint/__main__.py
ilint/linter.py
ilint/analyzer/__init__.py
ilint/analyzer/import_visitor.py
ilint/config/__init__.py
ilint/config/parser.py
ilint/validation/__init__.py
ilint/validation/contract.py
ilint-0.1.0.dist-info/METADATA
ilint-0.1.0.dist-info/WHEEL
ilint-0.1.0.dist-info/entry_points.txt
ilint-0.1.0.dist-info/licenses/LICENSE
ilint-0.1.0.dist-info/RECORD
